ipyflow/__init__.py
ipyflow/__main__.py
ipyflow/_version.py
ipyflow/comm_manager.py
ipyflow/config.py
ipyflow/flow.py
ipyflow/frontend.py
ipyflow/install.py
ipyflow/line_magics.py
ipyflow/models.py
ipyflow/py.typed
ipyflow/singletons.py
ipyflow/types.py
ipyflow/version.py
ipyflow/analysis/__init__.py
ipyflow/analysis/live_refs.py
ipyflow/analysis/mixins.py
ipyflow/analysis/resolved_symbols.py
ipyflow/analysis/symbol_edges.py
ipyflow/analysis/symbol_ref.py
ipyflow/analysis/utils.py
ipyflow/annotations/__init__.py
ipyflow/annotations/annotations.py
ipyflow/annotations/builtins.pyi
ipyflow/annotations/compiler.py
ipyflow/annotations/io.pyi
ipyflow/annotations/ipyflow.pyi
ipyflow/annotations/matplotlib.pyplot.pyi
ipyflow/annotations/random.pyi
ipyflow/annotations/sklearn.pyi
ipyflow/annotations/time.pyi
ipyflow/api/__init__.py
ipyflow/api/cells.py
ipyflow/api/lift.py
ipyflow/data_model/__init__.py
ipyflow/data_model/cell.py
ipyflow/data_model/namespace.py
ipyflow/data_model/scope.py
ipyflow/data_model/statement.py
ipyflow/data_model/symbol.py
ipyflow/data_model/timestamp.py
ipyflow/data_model/utils/__init__.py
ipyflow/data_model/utils/annotation_utils.py
ipyflow/data_model/utils/update_protocol.py
ipyflow/experimental/__init__.py
ipyflow/experimental/dag.py
ipyflow/kernel/__init__.py
ipyflow/kernel/__main__.py
ipyflow/kernel/install.py
ipyflow/kernel/kernel.py
ipyflow/kernel/patched_nest_asyncio.py
ipyflow/memoization/__init__.py
ipyflow/patches/__init__.py
ipyflow/patches/cloudpickle_patch.py
ipyflow/patches/pyspark_patch.py
ipyflow/pyccolo/__init__.py
ipyflow/shell/__init__.py
ipyflow/shell/interactiveshell.py
ipyflow/shell/interactiveshellembed.py
ipyflow/shell/terminalinteractiveshell.py
ipyflow/shell/zmqshell.py
ipyflow/slicing/__init__.py
ipyflow/slicing/context.py
ipyflow/slicing/mixin.py
ipyflow/tracing/__init__.py
ipyflow/tracing/flow_ast_rewriter.py
ipyflow/tracing/interrupt_tracer.py
ipyflow/tracing/ipyflow_tracer.py
ipyflow/tracing/output_recorder.py
ipyflow_core-0.0.226.dist-info/licenses/LICENSE.txt
ipyflow_core-0.0.226.dist-info/METADATA
ipyflow_core-0.0.226.dist-info/WHEEL
ipyflow_core-0.0.226.dist-info/top_level.txt
ipyflow_core-0.0.226.dist-info/RECORD
