Metadata-Version: 2.4
Name: ipyflow-core
Version: 0.0.226
Summary: Backend package for ipyflow's dataflow functionality
Home-page: https://github.com/ipyflow/ipyflow
Author: Stephen Macke
Author-email: stephen.macke@gmail.com
License: BSD-3-Clause
Classifier: Development Status :: 3 - Alpha
Classifier: Intended Audience :: Developers
Classifier: License :: OSI Approved :: BSD License
Classifier: Natural Language :: English
Classifier: Programming Language :: Python :: 3.6
Classifier: Programming Language :: Python :: 3.7
Classifier: Programming Language :: Python :: 3.8
Classifier: Programming Language :: Python :: 3.9
Classifier: Programming Language :: Python :: 3.10
Classifier: Programming Language :: Python :: 3.11
Classifier: Programming Language :: Python :: 3.12
Classifier: Programming Language :: Python :: 3.13
Classifier: Programming Language :: Python :: 3.14
Requires-Python: >=3.6
License-File: LICENSE.txt
Requires-Dist: astunparse
Requires-Dist: black
Requires-Dist: contextvars; python_version < "3.7"
Requires-Dist: ipykernel
Requires-Dist: ipython; python_version >= "3.9"
Requires-Dist: ipython<8.13; python_version >= "3.8" and python_version < "3.9"
Requires-Dist: ipython<=7.16; python_version < "3.8"
Requires-Dist: ipywidgets
Requires-Dist: nest_asyncio
Requires-Dist: pyccolo==0.0.82
Requires-Dist: traitlets
Provides-Extra: typecheck
Requires-Dist: mypy; extra == "typecheck"
Provides-Extra: test
Requires-Dist: black; extra == "test"
Requires-Dist: hypothesis; extra == "test"
Requires-Dist: isort; extra == "test"
Requires-Dist: mypy; extra == "test"
Requires-Dist: numpy; extra == "test"
Requires-Dist: pandas; extra == "test"
Requires-Dist: pytest; extra == "test"
Requires-Dist: pytest-cov; extra == "test"
Requires-Dist: ruff; extra == "test"
Requires-Dist: types-dataclasses; extra == "test"
Requires-Dist: types-contextvars; extra == "test"
Provides-Extra: dev
Requires-Dist: build; extra == "dev"
Requires-Dist: pycln; extra == "dev"
Requires-Dist: twine; extra == "dev"
Requires-Dist: versioneer; extra == "dev"
Requires-Dist: black; extra == "dev"
Requires-Dist: hypothesis; extra == "dev"
Requires-Dist: isort; extra == "dev"
Requires-Dist: mypy; extra == "dev"
Requires-Dist: numpy; extra == "dev"
Requires-Dist: pandas; extra == "dev"
Requires-Dist: pytest; extra == "dev"
Requires-Dist: pytest-cov; extra == "dev"
Requires-Dist: ruff; extra == "dev"
Requires-Dist: types-dataclasses; extra == "dev"
Requires-Dist: types-contextvars; extra == "dev"
Dynamic: license-file
